advene/__init__.py
advene/main.py
advene/core/__init__.py
advene/core/config.py
advene/core/controller.py
advene/core/corpustools.py
advene/core/idgenerator.py
advene/core/imagecache.py
advene/core/mediacontrol.py
advene/core/plugin.py
advene/core/version.py
advene/core/webcherry.py
advene/gui/__init__.py
advene/gui/actions.py
advene/gui/evaluator.py
advene/gui/main.py
advene/gui/menus.py
advene/gui/popup.py
advene/gui/widget.py
advene/gui/edit/__init__.py
advene/gui/edit/corpusmerge.py
advene/gui/edit/create.py
advene/gui/edit/dvdselect.py
advene/gui/edit/elements.py
advene/gui/edit/exporter.py
advene/gui/edit/frameselector.py
advene/gui/edit/htmleditor.py
advene/gui/edit/importer.py
advene/gui/edit/imports.py
advene/gui/edit/merge.py
advene/gui/edit/montage.py
advene/gui/edit/properties.py
advene/gui/edit/rules.py
advene/gui/edit/shapewidget.py
advene/gui/edit/tales.py
advene/gui/edit/timeadjustment.py
advene/gui/edit/transcribe.py
advene/gui/plugins/__init__.py
advene/gui/plugins/actions.py
advene/gui/plugins/contenthandlers.py
advene/gui/plugins/htmlcontenhandler.py
advene/gui/plugins/kinect.py
advene/gui/plugins/logmessages.py
advene/gui/plugins/packageimporter.py
advene/gui/plugins/shotvalidation.py
advene/gui/plugins/videoplayer.py
advene/gui/util/__init__.py
advene/gui/util/completer.py
advene/gui/util/dialog.py
advene/gui/util/initialconfig.py
advene/gui/util/playpausebutton.py
advene/gui/views/__init__.py
advene/gui/views/accumulatorpopup.py
advene/gui/views/activebookmarks.py
advene/gui/views/annotationdisplay.py
advene/gui/views/bookmarks.py
advene/gui/views/browser.py
advene/gui/views/caption.py
advene/gui/views/checker.py
advene/gui/views/corpusstatistics.py
advene/gui/views/editaccumulator.py
advene/gui/views/editionhistory.py
advene/gui/views/finder.py
advene/gui/views/html.py
advene/gui/views/interactivequery.py
advene/gui/views/logwindow.py
advene/gui/views/relation.py
advene/gui/views/relationdisplay.py
advene/gui/views/scroller.py
advene-3.15.dist-info/AUTHORS
advene-3.15.dist-info/COPYING
advene-3.15.dist-info/METADATA
advene-3.15.dist-info/WHEEL
advene-3.15.dist-info/top_level.txt
advene-3.15.dist-info/RECORD
