Metadata-Version: 2.2
Name: advene
Version: 3.15
Summary: Annotate DVds, Exchange on the NEt
Author-email: Olivier Aubert <contact@olivieraubert.net>, Pierre-Antoine Champin <pierre-antoine.champin@liris.cnrs.fr>, Yannick Prié <contact@yannickprie.net>
Maintainer-email: Olivier Aubert <contact@olivieraubert.net>
License: GPLv2+
Project-URL: Homepage, https://www.advene.org/
Project-URL: Documentation, https://www.advene.org/
Project-URL: Repository, https://github.com/oaubert/advene.git
Project-URL: Bug Tracker, https://github.com/oaubert/advene/issues
Project-URL: Changelog, https://github.com/oaubert/advene/blob/master/CHANGES.txt
Keywords: video,annotation,caqdas
Classifier: Environment :: X11 Applications :: GTK
Classifier: Environment :: Win32 (MS Windows)
Classifier: Environment :: MacOS X
Classifier: Development Status :: 5 - Production/Stable
Classifier: License :: OSI Approved :: GNU General Public License (GPL)
Classifier: Programming Language :: Python
Classifier: Intended Audience :: End Users/Desktop
Classifier: Operating System :: OS Independent
Classifier: Topic :: Multimedia :: Video :: Non-Linear Editor
License-File: COPYING
License-File: AUTHORS
Requires-Dist: CherryPy
Requires-Dist: requests
